ShiyanlouRubyJiaochengHeji20160904/README.md
ShiyanlouRubyJiaochengHeji20160904/__init__.py
ShiyanlouRubyJiaochengHeji20160904/__main__.py
ShiyanlouRubyJiaochengHeji20160904/file.epub
ShiyanlouRubyJiaochengHeji20160904/index.html
ShiyanlouRubyJiaochengHeji20160904/css/__init__.py
ShiyanlouRubyJiaochengHeji20160904/css/annotations.css
ShiyanlouRubyJiaochengHeji20160904/css/main.css
ShiyanlouRubyJiaochengHeji20160904/css/normalize.css
ShiyanlouRubyJiaochengHeji20160904/css/popup.css
ShiyanlouRubyJiaochengHeji20160904/font/__init__.py
ShiyanlouRubyJiaochengHeji20160904/font/fontello.eot
ShiyanlouRubyJiaochengHeji20160904/font/fontello.svg
ShiyanlouRubyJiaochengHeji20160904/font/fontello.ttf
ShiyanlouRubyJiaochengHeji20160904/font/fontello.woff
ShiyanlouRubyJiaochengHeji20160904/img/__init__.py
ShiyanlouRubyJiaochengHeji20160904/img/annotator-glyph-sprite.png
ShiyanlouRubyJiaochengHeji20160904/img/annotator-icon-sprite.png
ShiyanlouRubyJiaochengHeji20160904/img/apple-touch-icon.png
ShiyanlouRubyJiaochengHeji20160904/img/cancelfullscreen.png
ShiyanlouRubyJiaochengHeji20160904/img/close.png
ShiyanlouRubyJiaochengHeji20160904/img/fullscreen.png
ShiyanlouRubyJiaochengHeji20160904/img/loader.gif
ShiyanlouRubyJiaochengHeji20160904/img/menu-icon.png
ShiyanlouRubyJiaochengHeji20160904/img/save.png
ShiyanlouRubyJiaochengHeji20160904/img/saved.png
ShiyanlouRubyJiaochengHeji20160904/img/settings-s.png
ShiyanlouRubyJiaochengHeji20160904/img/settings.png
ShiyanlouRubyJiaochengHeji20160904/img/star.png
ShiyanlouRubyJiaochengHeji20160904/js/__init__.py
ShiyanlouRubyJiaochengHeji20160904/js/epub.js
ShiyanlouRubyJiaochengHeji20160904/js/epub.min.js
ShiyanlouRubyJiaochengHeji20160904/js/epub.min.map
ShiyanlouRubyJiaochengHeji20160904/js/hooks.min.js
ShiyanlouRubyJiaochengHeji20160904/js/hooks.min.map
ShiyanlouRubyJiaochengHeji20160904/js/reader.js
ShiyanlouRubyJiaochengHeji20160904/js/reader.js.map
ShiyanlouRubyJiaochengHeji20160904/js/reader.min.js
shiyanlou_ruby_jiaocheng_heji_20160904-2024.3.2.0.dist-info/METADATA
shiyanlou_ruby_jiaocheng_heji_20160904-2024.3.2.0.dist-info/WHEEL
shiyanlou_ruby_jiaocheng_heji_20160904-2024.3.2.0.dist-info/entry_points.txt
shiyanlou_ruby_jiaocheng_heji_20160904-2024.3.2.0.dist-info/top_level.txt
shiyanlou_ruby_jiaocheng_heji_20160904-2024.3.2.0.dist-info/RECORD
